twrpdtgen_v3/__init__.py
twrpdtgen_v3/__main__.py
twrpdtgen_v3/device_tree.py
twrpdtgen_v3/main.py
twrpdtgen_v3/proprietary_files/elf.py
twrpdtgen_v3/proprietary_files/get_vndk_libs.py
twrpdtgen_v3/proprietary_files/ignore.py
twrpdtgen_v3/proprietary_files/proprietary_files_list.py
twrpdtgen_v3/proprietary_files/section.py
twrpdtgen_v3/proprietary_files/sections/acdb.py
twrpdtgen_v3/proprietary_files/sections/adsp.py
twrpdtgen_v3/proprietary_files/sections/alarm.py
twrpdtgen_v3/proprietary_files/sections/ant.py
twrpdtgen_v3/proprietary_files/sections/atrace.py
twrpdtgen_v3/proprietary_files/sections/audio.py
twrpdtgen_v3/proprietary_files/sections/authsecret.py
twrpdtgen_v3/proprietary_files/sections/automotive.py
twrpdtgen_v3/proprietary_files/sections/bluetooth.py
twrpdtgen_v3/proprietary_files/sections/boot.py
twrpdtgen_v3/proprietary_files/sections/broadcastradio.py
twrpdtgen_v3/proprietary_files/sections/camera.py
twrpdtgen_v3/proprietary_files/sections/cas.py
twrpdtgen_v3/proprietary_files/sections/cdsp.py
twrpdtgen_v3/proprietary_files/sections/cit.py
twrpdtgen_v3/proprietary_files/sections/cne.py
twrpdtgen_v3/proprietary_files/sections/configstore.py
twrpdtgen_v3/proprietary_files/sections/confirmationui.py
twrpdtgen_v3/proprietary_files/sections/contexthub.py
twrpdtgen_v3/proprietary_files/sections/cvp.py
twrpdtgen_v3/proprietary_files/sections/display.py
twrpdtgen_v3/proprietary_files/sections/dpm.py
twrpdtgen_v3/proprietary_files/sections/drm.py
twrpdtgen_v3/proprietary_files/sections/dsp.py
twrpdtgen_v3/proprietary_files/sections/dumpstate.py
twrpdtgen_v3/proprietary_files/sections/face.py
twrpdtgen_v3/proprietary_files/sections/fastboot.py
twrpdtgen_v3/proprietary_files/sections/fingerprint.py
twrpdtgen_v3/proprietary_files/sections/fm.py
twrpdtgen_v3/proprietary_files/sections/gatekeeper.py
twrpdtgen_v3/proprietary_files/sections/gnss.py
twrpdtgen_v3/proprietary_files/sections/health.py
twrpdtgen_v3/proprietary_files/sections/identity.py
twrpdtgen_v3-3.1.1.dist-info/METADATA
twrpdtgen_v3-3.1.1.dist-info/WHEEL
twrpdtgen_v3-3.1.1.dist-info/entry_points.txt
twrpdtgen_v3-3.1.1.dist-info/RECORD
