Metadata-Version: 2.3
Name: twrpdtgen_v3
Version: 3.1.1
Summary: Create an Android device tree from a Firmware dump using dumpyara
License: Apache-2.0
Author: xXHenneBXx
Author-email: henneb93@gmail.com
Requires-Python: >=3.8,<4.0
Classifier: License :: OSI Approved :: Apache Software License
Classifier: Programming Language :: Python :: 3
Classifier: Programming Language :: Python :: 3.8
Classifier: Programming Language :: Python :: 3.9
Classifier: Programming Language :: Python :: 3.10
Classifier: Programming Language :: Python :: 3.11
Classifier: Programming Language :: Python :: 3.12
Classifier: Programming Language :: Python :: 3.13
Requires-Dist: GitPython (>=3.1.31,<4.0.0)
Requires-Dist: Jinja2 (>=3.1.6,<4.0.0)
Requires-Dist: sebaubuntu-libs (>=1.5.0,<2.0.0)
Project-URL: Repository, https://github.com/xXHenneBXx/twrpdtgen_v3
